ocp_viewer_mcp/__init__.py
ocp_viewer_mcp/server.py
ocp_viewer_mcp-0.1.0.dist-info/LICENSE
ocp_viewer_mcp-0.1.0.dist-info/METADATA
ocp_viewer_mcp-0.1.0.dist-info/WHEEL
ocp_viewer_mcp-0.1.0.dist-info/entry_points.txt
ocp_viewer_mcp-0.1.0.dist-info/RECORD
