Metadata-Version: 2.1
Name: ocp-viewer-mcp
Version: 0.1.0
Summary: MCP server for capturing screenshots from OCP CAD Viewer
Home-page: https://github.com/dmilad/ocp-viewer-mcp
License: MIT
Keywords: mcp,cadquery,build123d,ocp,cad,cursor,ai,screenshot
Author: Milad
Requires-Python: >=3.10,<4.0
Classifier: Development Status :: 4 - Beta
Classifier: Intended Audience :: Developers
Classifier: License :: OSI Approved :: MIT License
Classifier: Operating System :: OS Independent
Classifier: Programming Language :: Python :: 3
Classifier: Programming Language :: Python :: 3.10
Classifier: Programming Language :: Python :: 3.11
Classifier: Programming Language :: Python :: 3.12
Classifier: Topic :: Scientific/Engineering
Classifier: Topic :: Software Development :: Libraries :: Python Modules
Requires-Dist: mcp (>=1.0.0,<2.0.0)
Requires-Dist: ocp-vscode (>=3.0.0,<4.0.0)
Project-URL: Repository, https://github.com/dmilad/ocp-viewer-mcp
